estimateratio/__init__.py
estimateratio/estimate_ratio.py
estimateratio-0.0.5.dist-info/LICENSE
estimateratio-0.0.5.dist-info/METADATA
estimateratio-0.0.5.dist-info/WHEEL
estimateratio-0.0.5.dist-info/top_level.txt
estimateratio-0.0.5.dist-info/RECORD
