Metadata-Version: 2.1
Name: estimateratio
Version: 0.0.5
Summary: Estimate ratios of random variables
Home-page: https://gitlab.com/aaylward/estimateratio
Author: Anthony Aylward
Author-email: aaylward@salk.edu
License: UNKNOWN
Platform: UNKNOWN
Classifier: Programming Language :: Python :: 3
Classifier: License :: OSI Approved :: MIT License
Classifier: Operating System :: OS Independent
License-File: LICENSE
